tsops/__init__.py
tsops/main.py
tsops-0.1.1.dist-info/LICENSE
tsops-0.1.1.dist-info/METADATA
tsops-0.1.1.dist-info/WHEEL
tsops-0.1.1.dist-info/top_level.txt
tsops-0.1.1.dist-info/RECORD
